edx_event_bus_redis/__init__.py
edx_event_bus_redis/apps.py
edx_event_bus_redis/models.py
edx_event_bus_redis/urls.py
edx_event_bus_redis/internal/__init__.py
edx_event_bus_redis/internal/config.py
edx_event_bus_redis/internal/consumer.py
edx_event_bus_redis/internal/message.py
edx_event_bus_redis/internal/producer.py
edx_event_bus_redis/internal/utils.py
edx_event_bus_redis/management/__init__.py
edx_event_bus_redis/management/commands/__init__.py
edx_event_bus_redis/management/commands/produce_event.py
edx_event_bus_redis-0.6.1.dist-info/licenses/LICENSE.txt
edx_event_bus_redis-0.6.1.dist-info/METADATA
edx_event_bus_redis-0.6.1.dist-info/WHEEL
edx_event_bus_redis-0.6.1.dist-info/top_level.txt
edx_event_bus_redis-0.6.1.dist-info/RECORD
