Metadata-Version: 2.4
Name: edx_event_bus_redis
Version: 0.6.1
Summary: Redis Streams implementation for the Open edX event bus.
Home-page: https://github.com/openedx/event-bus-redis
Author: edX
Author-email: oscm@edx.org
License: AGPL-3.0-or-later
Keywords: Python edx
Classifier: Development Status :: 3 - Alpha
Classifier: Framework :: Django
Classifier: Framework :: Django :: 4.2
Classifier: Framework :: Django :: 5.2
Classifier: Intended Audience :: Developers
Classifier: Natural Language :: English
Classifier: Programming Language :: Python :: 3
Classifier: Programming Language :: Python :: 3.11
Classifier: Programming Language :: Python :: 3.12
Requires-Python: >=3.11
License-File: LICENSE.txt
Requires-Dist: Django
Requires-Dist: edx_django_utils
Requires-Dist: edx_toggles
Requires-Dist: openedx-events>=9.5.0
Requires-Dist: walrus
Dynamic: author
Dynamic: author-email
Dynamic: classifier
Dynamic: description
Dynamic: description-content-type
Dynamic: home-page
Dynamic: keywords
Dynamic: license
Dynamic: license-file
Dynamic: requires-dist
Dynamic: requires-python
Dynamic: summary
